hacker_tracker_application/__init__.py
hacker_tracker_application/homescreen.py
hacker_tracker_application/nlp.py
hacker_tracker_reeyagup-0.4.5.dist-info/LICENSE
hacker_tracker_reeyagup-0.4.5.dist-info/METADATA
hacker_tracker_reeyagup-0.4.5.dist-info/WHEEL
hacker_tracker_reeyagup-0.4.5.dist-info/entry_points.txt
hacker_tracker_reeyagup-0.4.5.dist-info/top_level.txt
hacker_tracker_reeyagup-0.4.5.dist-info/trend_data.txt
hacker_tracker_reeyagup-0.4.5.dist-info/RECORD
