Metadata-Version: 2.1
Name: hacker-tracker-reeyagup
Version: 0.4.5
Summary: A desktop application intended to track habits of the user and promote a healthier lifestyle.
Home-page: https://github.com/FastAndFerbious/HackerTracker
Author: Ferbious Ferby Team
Author-email: rgup@ufl.edu
License: UNKNOWN
Project-URL: Bug Tracker, https://github.com/FastAndFerbious/HackerTracker/issues
Platform: UNKNOWN
Classifier: Programming Language :: Python :: 3
Classifier: License :: OSI Approved :: MIT License
Classifier: Operating System :: OS Independent
Requires-Python: >=3.6
License-File: LICENSE
Requires-Dist: spacy (<4.0.0,>=3.0.0)
Requires-Dist: tkcalendar (==1.6.1)
Requires-Dist: nltk (==3.3)
Requires-Dist: spacytextblob (==3.0.1)
Requires-Dist: pandas (==1.2.5)
Requires-Dist: matplotlib (==3.4.2)
Requires-Dist: Click (==7.1.1)
Requires-Dist: wordcloud
